clld_glottologfamily_plugin/__init__.py
clld_glottologfamily_plugin/datatables.py
clld_glottologfamily_plugin/interfaces.py
clld_glottologfamily_plugin/maps.py
clld_glottologfamily_plugin/models.py
clld_glottologfamily_plugin/util.py
clld_glottologfamily_plugin/templates/family/detail_html.mako
clld_glottologfamily_plugin/templates/family/index_html.mako
clld_glottologfamily_plugin/templates/family/rdf.mako
clld_glottologfamily_plugin-4.1.0.dist-info/LICENSE
clld_glottologfamily_plugin-4.1.0.dist-info/METADATA
clld_glottologfamily_plugin-4.1.0.dist-info/WHEEL
clld_glottologfamily_plugin-4.1.0.dist-info/top_level.txt
clld_glottologfamily_plugin-4.1.0.dist-info/RECORD
