Metadata-Version: 2.1
Name: clld-glottologfamily-plugin
Version: 4.1.0
Summary: A clld plugin adding language family information from Glottolog
Home-page: https://github.com/clld/clld-glottologfamily-plugin
Author: Robert Forkel
Author-email: dlce.rdm@eva.mpg.de
License: Apache 2.0
Keywords: web pyramid clld
Platform: any
Classifier: Development Status :: 5 - Production/Stable
Classifier: Intended Audience :: Developers
Classifier: Natural Language :: English
Classifier: Operating System :: OS Independent
Classifier: Programming Language :: Python :: 3
Classifier: Programming Language :: Python :: 3.8
Classifier: Programming Language :: Python :: 3.9
Classifier: Programming Language :: Python :: 3.10
Classifier: Programming Language :: Python :: 3.11
Classifier: Programming Language :: Python :: 3.12
Classifier: License :: OSI Approved :: Apache Software License
Requires-Python: >=3.8
License-File: LICENSE
Requires-Dist: clld (>=7.0)
Requires-Dist: sqlalchemy
Requires-Dist: zope.interface
Requires-Dist: pybtex
Requires-Dist: pyglottolog (>=2.0)
Provides-Extra: dev
Requires-Dist: flake8 ; extra == 'dev'
Requires-Dist: wheel ; extra == 'dev'
Requires-Dist: build ; extra == 'dev'
Requires-Dist: twine ; extra == 'dev'
Provides-Extra: test
Requires-Dist: pytest (>=5) ; extra == 'test'
Requires-Dist: pytest-mock ; extra == 'test'
Requires-Dist: pytest-cov ; extra == 'test'
Requires-Dist: pytest-clld ; extra == 'test'
Requires-Dist: coverage (>=4.2) ; extra == 'test'
Requires-Dist: webtest ; extra == 'test'
